pynewyear/__init__.py
pynewyear/__main__.py
pynewyear-1.0.1.dist-info/LICENSE
pynewyear-1.0.1.dist-info/METADATA
pynewyear-1.0.1.dist-info/WHEEL
pynewyear-1.0.1.dist-info/top_level.txt
pynewyear-1.0.1.dist-info/RECORD
