Metadata-Version: 2.1
Name: pynewyear
Version: 1.0.1
Summary: Happy New Year! 🎄
Home-page: https://github.com/ijustbsd/pynewyear
Author: Baboshin Sergey
Author-email: ijustbsd@gmail.com
License: UNKNOWN
Platform: UNKNOWN
Classifier: Programming Language :: Python :: 3
Classifier: License :: OSI Approved :: MIT License
Classifier: Operating System :: OS Independent
Requires-Python: >=3.7
